tjawn/__init__.py
tjawn/lark_parser.py
tjawn/parser.py
tjawn/serializer.py
tjawn-1.0.0.dist-info/METADATA
tjawn-1.0.0.dist-info/WHEEL
tjawn-1.0.0.dist-info/RECORD
