Metadata-Version: 2.1
Name: tjawn
Version: 1.0.0
Summary: Human friendly lightweight object notation.
Author: tjkopena
Author-email: tjkopena@gmail.com
Requires-Python: >=3.10,<4.0
Classifier: Programming Language :: Python :: 3
Classifier: Programming Language :: Python :: 3.10
Classifier: Programming Language :: Python :: 3.11
